README.md
setup.py
screader/__init__.py
screader/decompress.py
screader/formatters.py
screader/generators.py
screader/tokens.py
screader.egg-info/PKG-INFO
screader.egg-info/SOURCES.txt
screader.egg-info/dependency_links.txt
screader.egg-info/entry_points.txt
screader.egg-info/top_level.txt
screader/commands/__init__.py
screader/commands/screader.py