Metadata-Version: 2.1
Name: screader
Version: 0.0.2
Summary: Extract text from Sam Coupe Entropy reader files (as seen on FRED).
Home-page: https://github.com/mfitzp/screader
Author: Martin Fitzpatrick
Author-email: martin.fitzpatrick@gmail.com
License: UNKNOWN
Platform: UNKNOWN
Classifier: Programming Language :: Python :: 3
Classifier: License :: OSI Approved :: MIT License
Classifier: Operating System :: OS Independent
Requires-Python: >=3.4
